test/__init__.py
test/test_form_val.py
generic_validator-0.2.dist-info/METADATA
generic_validator-0.2.dist-info/WHEEL
generic_validator-0.2.dist-info/top_level.txt
generic_validator-0.2.dist-info/RECORD
