Metadata-Version: 2.1
Name: generic-validator
Version: 0.2
Summary: Is a tool for validating, transforming, and controlling data.
Author: Garbi Youssef
Author-email: gharbiyoussef884@gmail.com
License: MIT
